<?xml version="1.0" encoding="utf-8" ?>
<dwsync>
<file name="about afc splat.psd" server="97.74.144.104" local="126858800257812500" remote="128906130600000000" />
<file name="background.psd" server="97.74.144.104" local="128901201350000000" remote="128906130600000000" />
<file name="contact us splat.psd" server="97.74.144.104" local="126858798308437500" remote="128906130600000000" />
<file name="fpbackdrop.psd" server="97.74.144.104" local="126858825300937500" remote="128906130600000000" />
<file name="giving splat.psd" server="97.74.144.104" local="126858797005000000" remote="128906130600000000" />
<file name="paintsplat1.png" server="97.74.144.104" local="128905033429232500" remote="128906130600000000" />
<file name="paintsplat2.png" server="97.74.144.104" local="126858789852812500" remote="128906130600000000" />
<file name="paintsplat3.png" server="97.74.144.104" local="128905033799388750" remote="128906130600000000" />
<file name="paintsplat4.png" server="97.74.144.104" local="128905033920170000" remote="128906130600000000" />
<file name="paintsplat4.psd" server="97.74.144.104" local="128905038496107500" remote="128906130600000000" />
<file name="paintsplat5.png" server="97.74.144.104" local="128905034050170000" remote="128906130600000000" />
<file name="paintsplat6.png" server="97.74.144.104" local="128905034158607500" remote="128906130600000000" />
<file name="splat2.psd" server="97.74.144.104" local="126858794815312500" remote="128906130600000000" />
<file name="splat4.png" server="97.74.144.104" local="126858795646875000" remote="128906130600000000" />
<file name="white.psd" server="97.74.144.104" local="128905904648031727" remote="128906131200000000" />
<file name="white2.png" server="97.74.144.104" local="128905904759594227" remote="128906131200000000" />
</dwsync>