<?xml version="1.0" encoding="utf-8" ?>
<dwsync>
<file name="connect-lists-through-tabs.html" server="97.74.144.104" local="128892756380000000" remote="128906128800000000" />
<file name="connect-lists.html" server="97.74.144.104" local="128892756380000000" remote="128906128800000000" />
<file name="default.html" server="97.74.144.104" local="128892756380000000" remote="128906128800000000" />
<file name="delay-start.html" server="97.74.144.104" local="128892756380000000" remote="128906128800000000" />
<file name="display-grid.html" server="97.74.144.104" local="128892756380000000" remote="128906128800000000" />
<file name="empty-lists.html" server="97.74.144.104" local="128892756380000000" remote="128906128800000000" />
<file name="index.html" server="97.74.144.104" local="128892756380000000" remote="128906128800000000" />
<file name="items.html" server="97.74.144.104" local="128892756380000000" remote="128906128800000000" />
<file name="placeholder.html" server="97.74.144.104" local="128892756380000000" remote="128906128800000000" />
<file name="portlets.html" server="97.74.144.104" local="128892756380000000" remote="128906128800000000" />
</dwsync>